gerapy_item_pipeline/__init__.py
gerapy_item_pipeline/__version__.py
gerapy_item_pipeline/mongodb.py
gerapy_item_pipeline/settings.py
gerapy_item_pipeline-0.1.3.dist-info/METADATA
gerapy_item_pipeline-0.1.3.dist-info/WHEEL
gerapy_item_pipeline-0.1.3.dist-info/top_level.txt
gerapy_item_pipeline-0.1.3.dist-info/RECORD
